ew_dsb_client_lib/__init__.py
ew_dsb_client_lib/dsb_client_lib.py
ew_dsb_client_lib/auth/__init__.py
ew_dsb_client_lib/auth/auth_service.py
ew_dsb_client_lib/auth/dtos/__init__.py
ew_dsb_client_lib/auth/dtos/get_user_did_response_dto.py
ew_dsb_client_lib/auth/dtos/get_user_response_dto.py
ew_dsb_client_lib/auth/dtos/get_user_roles_response_dto.py
ew_dsb_client_lib/auth/dtos/signin_response_dto.py
ew_dsb_client_lib/auth/entities/__init__.py
ew_dsb_client_lib/auth/entities/claim_data_entity.py
ew_dsb_client_lib/auth/entities/public_claim_entity.py
ew_dsb_client_lib/auth/entities/user_entity.py
ew_dsb_client_lib/auth/entities/user_jwt_entity.py
ew_dsb_client_lib/auth/entities/user_role_entity.py
ew_dsb_client_lib/auth/operations/__init__.py
ew_dsb_client_lib/auth/operations/mutation_auth_operation.py
ew_dsb_client_lib/auth/operations/query_auth_operation.py
ew_dsb_client_lib/channel/__init__.py
ew_dsb_client_lib/channel/channel_service.py
ew_dsb_client_lib/channel/dtos/__init__.py
ew_dsb_client_lib/channel/dtos/create_channel_dto.py
ew_dsb_client_lib/channel/dtos/create_channel_response_dto.py
ew_dsb_client_lib/channel/dtos/find_one_channel_dto.py
ew_dsb_client_lib/channel/dtos/find_one_channel_response_dto.py
ew_dsb_client_lib/channel/dtos/remove_channel_dto.py
ew_dsb_client_lib/channel/dtos/remove_channel_response_dto.py
ew_dsb_client_lib/channel/entities/__init__.py
ew_dsb_client_lib/channel/entities/channel_entity.py
ew_dsb_client_lib/channel/operations/__init__.py
ew_dsb_client_lib/channel/operations/mutation_channel_operation.py
ew_dsb_client_lib/channel/operations/query_channel_operation.py
ew_dsb_client_lib/crypto/__init__.py
ew_dsb_client_lib/crypto/crypto_service.py
ew_dsb_client_lib/crypto/entities/__init__.py
ew_dsb_client_lib/crypto/entities/jwt_header_entity.py
ew_dsb_client_lib/gqls/__init__.py
ew_dsb_client_lib/gqls/gql_service.py
ew_dsb_client_lib/gqls/entities/__init__.py
ew_dsb_client_lib/gqls/entities/headers_entity.py
ew_dsb_client_lib-0.1.2a1.dist-info/LICENSE
ew_dsb_client_lib-0.1.2a1.dist-info/METADATA
ew_dsb_client_lib-0.1.2a1.dist-info/WHEEL
ew_dsb_client_lib-0.1.2a1.dist-info/top_level.txt
ew_dsb_client_lib-0.1.2a1.dist-info/RECORD
